odoo8_addon_crm_timesheet_analytic_partner-8.0.1.0.0-py2.7-nspkg.pth
odoo8_addon_crm_timesheet_analytic_partner-8.0.1.0.0.dist-info/top_level.txt
odoo8_addon_crm_timesheet_analytic_partner-8.0.1.0.0.dist-info/WHEEL
odoo8_addon_crm_timesheet_analytic_partner-8.0.1.0.0.dist-info/RECORD
odoo8_addon_crm_timesheet_analytic_partner-8.0.1.0.0.dist-info/metadata.json
odoo8_addon_crm_timesheet_analytic_partner-8.0.1.0.0.dist-info/DESCRIPTION.rst
odoo8_addon_crm_timesheet_analytic_partner-8.0.1.0.0.dist-info/METADATA
odoo8_addon_crm_timesheet_analytic_partner-8.0.1.0.0.dist-info/namespace_packages.txt
odoo_addons/crm_timesheet_analytic_partner/__openerp__.py
odoo_addons/crm_timesheet_analytic_partner/__init__.py
odoo_addons/crm_timesheet_analytic_partner/README.rst
odoo_addons/crm_timesheet_analytic_partner/models/__init__.py
odoo_addons/crm_timesheet_analytic_partner/models/crm_phonecall.py
odoo_addons/crm_timesheet_analytic_partner/tests/__init__.py
odoo_addons/crm_timesheet_analytic_partner/tests/test_crm_phonecall.py
odoo_addons/crm_timesheet_analytic_partner/images/phone_call_partner.png
