Metadata-Version: 2.0
Name: odoo8-addon-crm-timesheet-analytic-partner
Version: 8.0.1.0.0
Summary: CRM Timesheet Analytic Partner
Home-page: http://www.antiun.com
Author: UNKNOWN
Author-email: UNKNOWN
License: AGPL-3
Platform: UNKNOWN
Requires-Dist: odoo (<9.0a,>=8.0a)
Requires-Dist: odoo8-addon-analytic-partner-hr-timesheet
Requires-Dist: odoo8-addon-crm-timesheet
Classifier: Programming Language :: Python :: 2.7
Classifier: Framework :: Odoo
Classifier: License :: OSI Approved :: GNU Affero General Public License v3
